utils/__init__.py
utils/utils.py
ve_utils/__init__.py
ve_utils/ujson.py
ve_utils/usys.py
ve_utils/utils.py
ve_utils/utime.py
ve_utils/utype.py
ve_utils-2.5.3.dist-info/LICENSE
ve_utils-2.5.3.dist-info/METADATA
ve_utils-2.5.3.dist-info/WHEEL
ve_utils-2.5.3.dist-info/top_level.txt
ve_utils-2.5.3.dist-info/RECORD
