Metadata-Version: 2.1
Name: ve-utils
Version: 2.5.3
Summary: Utilities helper library for Python
Home-page: https://github.com/mano8/ve_utils
Author: Eli Serra
Author-email: eli.serra173@gmail.com
License: MIT
Classifier: License :: OSI Approved :: MIT License
Classifier: Programming Language :: Python :: 3
Classifier: Programming Language :: Python :: 3.7
Requires-Python: >=3.5
License-File: LICENSE
Provides-Extra: json
Requires-Dist: simplejson ; extra == 'json'
Provides-Extra: test
Requires-Dist: pytest ; extra == 'test'
Requires-Dist: coverage ; extra == 'test'
Requires-Dist: simplejson ; extra == 'test'
